{
   "bindings" : {
      "/actions/legacy" : {
         "poses" : [
            {
               "output" : "/actions/legacy/in/Left_Pose",
               "path" : "/user/hand/left/pose/raw"
            },
            {
               "output" : "/actions/legacy/in/Right_Pose",
               "path" : "/user/hand/right/pose/raw"
            }
         ],
        "sources": [
         
        ]
      },
   },
   "controller_type" : "glove",
   "description" : "Default binding values for legacy app using glove controller",
   "name" : "glove legacy defaults",
   "simulated_actions" : []
}
